LICENSE
MANIFEST.in
README.rst
setup.cfg
setup.py
versioneer.py
etc/requirements.txt
etc/requirements_blaze.txt
etc/requirements_dev.txt
etc/requirements_docs.txt
etc/requirements_ib.txt
etc/requirements_talib.txt
zipline/__init__.py
zipline/__main__.py
zipline/_protocol.pyx
zipline/_version.py
zipline/algorithm.py
zipline/algorithm_live.py
zipline/api.py
zipline/api.pyi
zipline/dispatch.py
zipline/errors.py
zipline/protocol.py
zipline/test_algorithms.py
zipline/zipline_warnings.py
zipline/assets/__init__.py
zipline/assets/_assets.pyx
zipline/assets/asset_db_migrations.py
zipline/assets/asset_db_schema.py
zipline/assets/asset_writer.py
zipline/assets/assets.py
zipline/assets/continuous_futures.pyx
zipline/assets/futures.py
zipline/assets/roll_finder.py
zipline/assets/synthetic.py
zipline/data/__init__.py
zipline/data/_adjustments.pyx
zipline/data/_equities.pyx
zipline/data/_minute_bar_internal.pyx
zipline/data/_resample.pyx
zipline/data/bar_reader.py
zipline/data/benchmarks.py
zipline/data/continuous_future_reader.py
zipline/data/data_portal.py
zipline/data/data_portal_live.py
zipline/data/dispatch_bar_reader.py
zipline/data/history_loader.py
zipline/data/loader.py
zipline/data/minute_bars.py
zipline/data/resample.py
zipline/data/session_bars.py
zipline/data/treasuries.py
zipline/data/treasuries_can.py
zipline/data/us_equity_pricing.py
zipline/data/bundles/__init__.py
zipline/data/bundles/core.py
zipline/data/bundles/csvdir.py
zipline/data/bundles/quandl.py
zipline/examples/__init__.py
zipline/examples/buy_and_hold.py
zipline/examples/buyapple.py
zipline/examples/dual_ema_talib.py
zipline/examples/dual_moving_average.py
zipline/examples/momentum_pipeline.py
zipline/examples/olmar.py
zipline/finance/__init__.py
zipline/finance/asset_restrictions.py
zipline/finance/blotter.py
zipline/finance/blotter_live.py
zipline/finance/cancel_policy.py
zipline/finance/commission.py
zipline/finance/constants.py
zipline/finance/controls.py
zipline/finance/execution.py
zipline_live.egg-info/PKG-INFO
zipline_live.egg-info/SOURCES.txt
zipline_live.egg-info/dependency_links.txt
zipline_live.egg-info/entry_points.txt
zipline_live.egg-info/requires.txt
zipline_live.egg-info/top_level.txt