Metadata-Version: 2.1
Name: zipline-live
Version: 1.1.0.5
Summary: A backtester and live trader for financial algorithms.
Home-page: http://zipline-live.io
Author: zipline-live community
Author-email: community@zipline-live.io
License: Apache 2.0
Platform: UNKNOWN
Classifier: Development Status :: 3 - Alpha
Classifier: License :: OSI Approved :: Apache Software License
Classifier: Natural Language :: English
Classifier: Programming Language :: Python
Classifier: Programming Language :: Python :: 2.7
Classifier: Programming Language :: Python :: 3.4
Classifier: Programming Language :: Python :: 3.5
Classifier: Operating System :: OS Independent
Classifier: Intended Audience :: Science/Research
Classifier: Topic :: Office/Business :: Financial
Classifier: Topic :: Scientific/Engineering :: Information Analysis
Classifier: Topic :: System :: Distributed Computing
Provides-Extra: all
Provides-Extra: ib
Provides-Extra: dev
Provides-Extra: talib
